setup.py
approxeng/__init__.py
approxeng.reimage.egg-info/PKG-INFO
approxeng.reimage.egg-info/SOURCES.txt
approxeng.reimage.egg-info/dependency_links.txt
approxeng.reimage.egg-info/top_level.txt
approxeng/reimage/__init__.py
approxeng/reimage/config_files.py
approxeng/reimage/util.py