Metadata-Version: 2.1
Name: approxeng.reimage
Version: 0.0.1
Summary: Library to modify SD card images, in particular for the Raspbery Pi OS
Home-page: https://github.com/ApproxEng/approxeng.reimage/
Author: Tom Oinn
Author-email: tomoinn@gmail.com
License: ASL2.0
Platform: UNKNOWN
Classifier: Programming Language :: Python :: 3.7
